jabu/__init__.py
jabu/encrypt.py
jabu/exceptions.py
jabu/main.py
jabu/stats.py
jabu/destinations/__init__.py
jabu/destinations/destination.py
jabu/destinations/folder.py
jabu/destinations/samba.py
jabu/notifications/__init__.py
jabu/notifications/notification.py
jabu/notifications/smtp.py
jabu/notifications/telegram.py
jabu/sources/__init__.py
jabu/sources/folder.py
jabu/sources/mysql.py
jabu/sources/source.py
jabu-0.2.1.dist-info/DESCRIPTION.rst
jabu-0.2.1.dist-info/METADATA
jabu-0.2.1.dist-info/RECORD
jabu-0.2.1.dist-info/WHEEL
jabu-0.2.1.dist-info/entry_points.txt
jabu-0.2.1.dist-info/metadata.json
jabu-0.2.1.dist-info/top_level.txt
