Metadata-Version: 2.0
Name: jabu
Version: 0.2.1
Summary: Just Another Backup Utility
Home-page: https://gitlab.com/carbans/jabu
Author: Carlos Latorre
Author-email: me@carloslatorre.net
License: GPL3
Keywords: backup jabu system sysadmin
Platform: UNKNOWN
Classifier: Development Status :: 3 - Alpha
Classifier: Intended Audience :: System Administrators
Classifier: Topic :: System :: Archiving :: Backup
Classifier: License :: OSI Approved :: GNU General Public License v3 (GPLv3)
Classifier: Programming Language :: Python :: 2
Classifier: Programming Language :: Python :: 2.6
Classifier: Programming Language :: Python :: 2.7
Classifier: Programming Language :: Python :: 3
Classifier: Programming Language :: Python :: 3.2
Classifier: Programming Language :: Python :: 3.3
Classifier: Programming Language :: Python :: 3.4
Classifier: Programming Language :: Python :: 3.5
Classifier: Programming Language :: Python :: 3.6
Requires-Dist: fnmatch
Requires-Dist: os
Requires-Dist: shutil
Requires-Dist: datetime
Requires-Dist: subprocess
